LICENSE
MANIFEST.in
README.md
setup.cfg
setup.py
acoustics/__init__.py
acoustics/_signal.py
acoustics/aio.py
acoustics/ambisonics.py
acoustics/atmosphere.py
acoustics/bands.py
acoustics/building.py
acoustics/cepstrum.py
acoustics/criterion.py
acoustics/decibel.py
acoustics/descriptors.py
acoustics/directivity.py
acoustics/doppler.py
acoustics/generator.py
acoustics/imaging.py
acoustics/octave.py
acoustics/power.py
acoustics/quantity.py
acoustics/reflection.py
acoustics/room.py
acoustics/signal.py
acoustics/utils.py
acoustics/weighting.py
acoustics.egg-info/PKG-INFO
acoustics.egg-info/SOURCES.txt
acoustics.egg-info/dependency_links.txt
acoustics.egg-info/requires.txt
acoustics.egg-info/top_level.txt
acoustics.egg-info/zip-safe
acoustics/data/iec_61672_1_2013.csv
acoustics/standards/__init__.py
acoustics/standards/iec_61260_1_2014.py
acoustics/standards/iec_61672_1_2013.py
acoustics/standards/iso_1683_2015.py
acoustics/standards/iso_1996_1_2003.py
acoustics/standards/iso_1996_2_2007.py
acoustics/standards/iso_9613_1_1993.py
acoustics/standards/iso_tr_25417_2007.py
data/WAV_LICENSE.md
data/absorption_coefficient.csv
data/ir_sportscentre_omni.wav
data/living_room_1.wav
data/cirrus/det_global_0010ms_comma_1dec.csv
data/cirrus/det_global_0010ms_comma_2dec.csv
data/cirrus/det_global_0010ms_semicolon_1dec.csv
data/cirrus/det_global_0010ms_semicolon_2dec.csv
data/cirrus/det_global_0063ms_comma_1dec.csv
data/cirrus/det_global_0063ms_comma_2dec.csv
data/cirrus/det_global_0063ms_semicolon_1dec.csv
data/cirrus/det_global_0063ms_semicolon_2dec.csv
data/cirrus/det_global_0250ms_comma_1dec.csv
data/cirrus/det_global_0250ms_comma_2dec.csv
data/cirrus/det_global_0250ms_semicolon_1dec.csv
data/cirrus/det_global_0250ms_semicolon_2dec.csv
data/cirrus/det_global_0500ms_comma_1dec.csv
data/cirrus/det_global_0500ms_comma_2dec.csv
data/cirrus/det_global_0500ms_semicolon_1dec.csv
data/cirrus/det_global_0500ms_semicolon_2dec.csv
data/cirrus/det_global_1000ms_comma_1dec.csv
data/cirrus/det_global_1000ms_comma_2dec.csv
data/cirrus/det_global_1000ms_semicolon_1dec.csv
data/cirrus/det_global_1000ms_semicolon_2dec.csv
data/cirrus/det_global_2000ms_comma_1dec.csv
