Metadata-Version: 2.1
Name: acoustics
Version: 0.2.2
Summary: Acoustics module for Python.
Home-page: UNKNOWN
Author: Python Acoustics
License: BSD 3-Clause License
Platform: UNKNOWN
Requires-Python: >=3.6.*
Provides-Extra: jit
Provides-Extra: documentation
Provides-Extra: fast_fft
